tests/__init__.py
tests/test_cli.py
yaml_to_sqlite/__init__.py
yaml_to_sqlite/cli.py
yaml_to_sqlite-1.0.dist-info/LICENSE
yaml_to_sqlite-1.0.dist-info/METADATA
yaml_to_sqlite-1.0.dist-info/WHEEL
yaml_to_sqlite-1.0.dist-info/entry_points.txt
yaml_to_sqlite-1.0.dist-info/top_level.txt
yaml_to_sqlite-1.0.dist-info/RECORD
