Metadata-Version: 2.1
Name: yaml-to-sqlite
Version: 1.0
Summary: Utility for converting YAML files to SQLite
Home-page: https://github.com/simonw/yaml-to-sqlite
Author: Simon Willison
License: Apache License, Version 2.0
Platform: UNKNOWN
Classifier: Development Status :: 3 - Alpha
Classifier: Intended Audience :: Developers
Classifier: Intended Audience :: Science/Research
Classifier: Intended Audience :: End Users/Desktop
Classifier: License :: OSI Approved :: Apache Software License
Classifier: Programming Language :: Python :: 3.6
Classifier: Programming Language :: Python :: 3.7
Requires-Dist: click
Requires-Dist: PyYAML
Requires-Dist: sqlite-utils (>=3.9.1)
Provides-Extra: test
Requires-Dist: pytest ; extra == 'test'
